[
  {
    "title": "Rust Concurrency",
    "link": "#rust-concurrency"
  },
  {
    "title": "Parallel Computing",
    "link": "#parallel-computing"
  },
  {
    "title": "Best Practices",
    "link": "#best-practices"
  },
  {
    "title": "Design Patterns",
    "link": "#design-patterns",
    "children": [
      {
        "title": "Map-Reduce",
        "link": "#map-reduce"
      },
      {
        "title": "Fork-Join:",
        "link": "#fork-join"
      },
      {
        "title": "Data Parallelism:",
        "link": "#data-parallelism"
      },
      {
        "title": "Producer-Consumer",
        "link": "#producer-consumer"
      },
      {
        "title": "Concurrency Safety",
        "link": "#concurrency-safety"
      }
    ]
  },
  {
    "title": "Disadvantages & Limitations",
    "link": "#disadvantages-limitations"
  },
  {
    "title": "Non-blocking processes",
    "link": "#non-blocking-processes"
  },
  {
    "title": "Conclusion",
    "link": "#conclusion"
  }
]
