[
  {
    "title": "Rust Syntax",
    "link": "#rust-syntax",
    "children": [
      {
        "title": "Syntax Rules",
        "link": "#rules"
      },
      {
        "title": "Basic Elements",
        "link": "#basic",
        "children": [
          {
            "title": "Comments",
            "link": "#comments"
          },
          {
            "title": "Code Block",
            "link": "#code-block"
          },
          {
            "title": "Indentation",
            "link": "#indentation"
          }
        ]
      },
      {
        "title": "Variables",
        "link": "#variables"
      },
      {
        "title": "Public Elements",
        "link": "#public"
      },
      {
        "title": "Operators",
        "link": "#operators",
        "children": [
          {
            "title": "Assign Operators",
            "link": "#assign-operators"
          },
          {
            "title": "Numeric Operators",
            "link": "#numeric-operators"
          },
          {
            "title": "Logic operators",
            "link": "#logic-operators"
          }
        ]
      },
      {
        "title": "Delimiters",
        "link": "#delimiters"
      },
      {
        "title": "Keywords",
        "link": "#keywords"
      }
    ]
  }
]
