{
  "timestamp": "2026-07-13T14:26:49.448756+00:00",
  "apply": false,
  "mode": "copy",
  "total": 30,
  "done": 0,
  "noop": 24,
  "planned": 6,
  "missing": 0,
  "operations": [
    {
      "action": "COPY",
      "source": "roadmap\\index.html",
      "target": "roadmap\\index.html",
      "status": "noop"
    },
    {
      "action": "COPY",
      "source": "roadmap\\community.html",
      "target": "roadmap\\community.html",
      "status": "noop"
    },
    {
      "action": "COPY",
      "source": "roadmap\\legal.html",
      "target": "roadmap\\legal.html",
      "status": "noop"
    },
    {
      "action": "COPY",
      "source": "roadmap\\manifesto.html",
      "target": "roadmap\\manifesto.html",
      "status": "noop"
    },
    {
      "action": "COPY",
      "source": "assets\\css\\sage.css",
      "target": "assets\\css\\sage.css",
      "status": "noop"
    },
    {
      "action": "COPY",
      "source": "assets\\css\\carousel.css",
      "target": "assets\\css\\carousel.css",
      "status": "noop"
    },
    {
      "action": "COPY",
      "source": "assets\\css\\manifesto.css",
      "target": "assets\\css\\manifesto.css",
      "status": "noop"
    },
    {
      "action": "COPY",
      "source": "assets\\css\\prism.css",
      "target": "assets\\css\\prism.css",
      "status": "noop"
    },
    {
      "action": "COPY",
      "source": "assets\\js\\sage.js",
      "target": "assets\\js\\sage.js",
      "status": "noop"
    },
    {
      "action": "COPY",
      "source": "assets\\js\\sidebar.js",
      "target": "assets\\js\\sidebar.js",
      "status": "noop"
    },
    {
      "action": "COPY",
      "source": "assets\\js\\progress.js",
      "target": "assets\\js\\progress.js",
      "status": "noop"
    },
    {
      "action": "COPY",
      "source": "assets\\js\\home.js",
      "target": "assets\\js\\home.js",
      "status": "noop"
    },
    {
      "action": "COPY",
      "source": "assets\\js\\prism.js",
      "target": "assets\\js\\prism.js",
      "status": "noop"
    },
    {
      "action": "COPY",
      "source": "manual\\progress.js",
      "target": "assets\\js\\progress.js",
      "status": "planned"
    },
    {
      "action": "COPY",
      "source": "manual\\progress-legacy.js",
      "target": "assets\\js\\progress-legacy.js",
      "status": "planned"
    },
    {
      "action": "COPY",
      "source": "manual\\sidebar.js",
      "target": "assets\\js\\sidebar.js",
      "status": "planned"
    },
    {
      "action": "COPY",
      "source": "manual\\lab-progress-bridge.js",
      "target": "assets\\js\\lab-progress-bridge.js",
      "status": "planned"
    },
    {
      "action": "COPY",
      "source": "manual\\topic-loader.js",
      "target": "assets\\js\\topic-loader.js",
      "status": "planned"
    },
    {
      "action": "COPY",
      "source": "manual\\roadmap.js",
      "target": "assets\\js\\roadmap.js",
      "status": "planned"
    },
    {
      "action": "COPY",
      "source": "roadmap\\robots.txt",
      "target": "roadmap\\robots.txt",
      "status": "noop"
    },
    {
      "action": "COPY",
      "source": "roadmap\\sitemap.xml",
      "target": "roadmap\\sitemap.xml",
      "status": "noop"
    },
    {
      "action": "COPY",
      "source": "assets\\fonts\\DejaVuSansMono.ttf",
      "target": "assets\\fonts\\DejaVuSansMono.ttf",
      "status": "noop"
    },
    {
      "action": "COPY",
      "source": "assets\\fonts\\ShareTechMono.ttf",
      "target": "assets\\fonts\\ShareTechMono.ttf",
      "status": "noop"
    },
    {
      "action": "COPY",
      "source": "assets\\topic_template.html",
      "target": "assets\\topic_template.html",
      "status": "noop"
    },
    {
      "action": "COPY",
      "source": "assets\\roadmap_template.html",
      "target": "assets\\roadmap_template.html",
      "status": "noop"
    },
    {
      "action": "COPY",
      "source": "assets\\images",
      "target": "assets\\images",
      "status": "noop"
    },
    {
      "action": "COPY",
      "source": "roadmap\\cse",
      "target": "roadmap\\cse",
      "status": "noop"
    },
    {
      "action": "COPY",
      "source": "roadmap\\csp",
      "target": "roadmap\\csp",
      "status": "noop"
    },
    {
      "action": "COPY",
      "source": "projects",
      "target": "projects",
      "status": "noop"
    },
    {
      "action": "COPY",
      "source": "roadmap\\labs\\videos",
      "target": "roadmap\\labs\\videos",
      "status": "noop"
    }
  ]
}